{
  "a0_checkpoint": "/sda/home/wangyuxin/ConvIR-B/checkpoints/official/Haze4K/haze4k-base.pkl",
  "bank_metrics": [
    {
      "bank_name": "A0_L3_full",
      "chosen_action_counts": {
        "A0@0": 210,
        "L3_balanced@1": 390
      },
      "chosen_variant_counts": {
        "A0": 210,
        "l3_fdf_lite_s004_g015_bm2": 390
      },
      "count": 600,
      "coverage": 1.0,
      "dSSIM": 1.7696619033813475e-05,
      "easy_top25_dPSNR": 0.12021402994791666,
      "fold": 0,
      "hard_bottom25_dPSNR": 0.08468887329101563,
      "intervention_rate": 0.65,
      "mean_chosen_alpha": 0.65,
      "mean_dPSNR": 0.1010397466023763,
      "positive_ratio": 0.65,
      "seed": 2026,
      "strong_count_le_-0.05": 0,
      "strong_per_600": 0.0,
      "strong_reference_cut_psnr": 42.755948066711426,
      "strong_reference_regression_count": 0,
      "true_vs_normal": 0.08066449165344239,
      "true_vs_shuffle": 0.074141845703125,
      "true_vs_zero": 0.10037472407023112,
      "utility_mode": "max_dpsnr",
      "worst_count_le_-0.20": 0,
      "worst_per_600": 0.0
    },
    {
      "bank_name": "A0_L3_full",
      "chosen_action_counts": {
        "A0@0": 214,
        "L3_balanced@1": 386
      },
      "chosen_variant_counts": {
        "A0": 214,
        "l3_fdf_lite_s004_g015_bm2": 386
      },
      "count": 600,
      "coverage": 1.0,
      "dSSIM": 1.900861660639445e-05,
      "easy_top25_dPSNR": 0.11985687255859374,
      "fold": 0,
      "hard_bottom25_dPSNR": 0.08434842427571615,
      "intervention_rate": 0.6433333333333333,
      "mean_chosen_alpha": 0.6433333333333333,
      "mean_dPSNR": 0.1008653195699056,
      "positive_ratio": 0.6433333333333333,
      "seed": 2026,
      "strong_count_le_-0.05": 0,
      "strong_per_600": 0.0,
      "strong_reference_cut_psnr": 42.755948066711426,
      "strong_reference_regression_count": 0,
      "true_vs_normal": 0.08036199251810709,
      "true_vs_shuffle": 0.07387201944986979,
      "true_vs_zero": 0.10003973642985026,
      "utility_mode": "tail_averse",
      "worst_count_le_-0.20": 0,
      "worst_per_600": 0.0
    },
    {
      "bank_name": "A0_L3_full",
      "chosen_action_counts": {
        "A0@0": 255,
        "L3_balanced@1": 345
      },
      "chosen_variant_counts": {
        "A0": 255,
        "l3_fdf_lite_s004_g015_bm2": 345
      },
      "count": 600,
      "coverage": 1.0,
      "dSSIM": 2.2386610507965087e-05,
      "easy_top25_dPSNR": 0.11760790506998697,
      "fold": 0,
      "hard_bottom25_dPSNR": 0.0809458033243815,
      "intervention_rate": 0.575,
      "mean_chosen_alpha": 0.575,
      "mean_dPSNR": 0.09755478223164876,
      "positive_ratio": 0.575,
      "seed": 2026,
      "strong_count_le_-0.05": 0,
      "strong_per_600": 0.0,
      "strong_reference_cut_psnr": 42.755948066711426,
      "strong_reference_regression_count": 0,
      "true_vs_normal": 0.07461772918701172,
      "true_vs_shuffle": 0.06830220858256023,
      "true_vs_zero": 0.09369677861531575,
      "utility_mode": "ssim_guarded",
      "worst_count_le_-0.20": 0,
      "worst_per_600": 0.0
    },
    {
      "bank_name": "A0_L3_shrink",
      "chosen_action_counts": {
        "A0@0": 196,
        "L3_balanced@0.25": 8,
        "L3_balanced@0.5": 13,
        "L3_balanced@0.75": 9,
        "L3_balanced@1": 374
      },
      "chosen_variant_counts": {
        "A0": 196,
        "l3_fdf_lite_s004_g015_bm2": 404
      },
      "count": 600,
      "coverage": 1.0,
      "dSSIM": 1.8277664979298908e-05,
      "easy_top25_dPSNR": 0.12066080729166667,
      "fold": 0,
      "hard_bottom25_dPSNR": 0.08469426472981771,
      "intervention_rate": 0.6733333333333333,
      "mean_chosen_alpha": 0.64875,
      "mean_dPSNR": 0.10123343785603842,
      "positive_ratio": 0.6733333333333333,
      "seed": 2026,
      "strong_count_le_-0.05": 0,
      "strong_per_600": 0.0,
      "strong_reference_cut_psnr": 42.755948066711426,
      "strong_reference_regression_count": 0,
      "true_vs_normal": 0.08079497337341308,
      "true_vs_shuffle": 0.0743648338317871,
      "true_vs_zero": 0.10069239298502604,
      "utility_mode": "max_dpsnr",
      "worst_count_le_-0.20": 0,
      "worst_per_600": 0.0
    },
    {
      "bank_name": "A0_L3_shrink",
      "chosen_action_counts": {
        "A0@0": 197,
        "L3_balanced@0.25": 9,
        "L3_balanced@0.5": 15,
        "L3_balanced@0.75": 11,
        "L3_balanced@1": 368
      },
      "chosen_variant_counts": {
        "A0": 197,
        "l3_fdf_lite_s004_g015_bm2": 403
      },
      "count": 600,
      "coverage": 1.0,
      "dSSIM": 1.9719898700714113e-05,
      "easy_top25_dPSNR": 0.12032198588053386,
      "fold": 0,
      "hard_bottom25_dPSNR": 0.08434069315592448,
      "intervention_rate": 0.6716666666666666,
      "mean_chosen_alpha": 0.6433333333333333,
      "mean_dPSNR": 0.10105985005696615,
      "positive_ratio": 0.6716666666666666,
      "seed": 2026,
      "strong_count_le_-0.05": 0,
      "strong_per_600": 0.0,
      "strong_reference_cut_psnr": 42.755948066711426,
      "strong_reference_regression_count": 0,
      "true_vs_normal": 0.08059918403625488,
      "true_vs_shuffle": 0.07411596298217774,
      "true_vs_zero": 0.10034317016601563,
      "utility_mode": "tail_averse",
      "worst_count_le_-0.20": 0,
      "worst_per_600": 0.0
    },
    {
      "bank_name": "A0_L3_shrink",
      "chosen_action_counts": {
        "A0@0": 212,
        "L3_balanced@0.25": 21,
        "L3_balanced@0.5": 25,
        "L3_balanced@0.75": 14,
        "L3_balanced@1": 328
      },
      "chosen_variant_counts": {
        "A0": 212,
        "l3_fdf_lite_s004_g015_bm2": 388
      },
      "count": 600,
      "coverage": 1.0,
      "dSSIM": 2.2816757361094157e-05,
      "easy_top25_dPSNR": 0.11790712992350261,
      "fold": 0,
      "hard_bottom25_dPSNR": 0.08120728810628255,
      "intervention_rate": 0.6466666666666666,
      "mean_chosen_alpha": 0.59375,
      "mean_dPSNR": 0.09804038047790527,
      "positive_ratio": 0.6466666666666666,
      "seed": 2026,
      "strong_count_le_-0.05": 0,
      "strong_per_600": 0.0,
      "strong_reference_cut_psnr": 42.755948066711426,
      "strong_reference_regression_count": 0,
      "true_vs_normal": 0.07631645202636719,
      "true_vs_shuffle": 0.06989057858784993,
      "true_vs_zero": 0.09528875350952148,
      "utility_mode": "ssim_guarded",
      "worst_count_le_-0.20": 0,
      "worst_per_600": 0.0
    },
    {
      "bank_name": "A0_L2_L3_L1_full",
      "chosen_action_counts": {
        "A0@0": 193,
        "L1_high_gain@1": 340,
        "L2_tail_safe@1": 43,
        "L3_balanced@1": 24
      },
      "chosen_variant_counts": {
        "A0": 193,
        "l1_fdf_lite_s004_g025_bm2": 340,
        "l2_fdf_lite_s002_g025_bm2": 43,
        "l3_fdf_lite_s004_g015_bm2": 24
      },
      "count": 600,
      "coverage": 1.0,
      "dSSIM": 1.98859969774882e-05,
      "easy_top25_dPSNR": 0.1470032755533854,
      "fold": 0,
      "hard_bottom25_dPSNR": 0.09999661763509114,
      "intervention_rate": 0.6783333333333333,
      "mean_chosen_alpha": 0.6783333333333333,
      "mean_dPSNR": 0.1233262825012207,
      "positive_ratio": 0.6783333333333333,
      "seed": 2026,
      "strong_count_le_-0.05": 0,
      "strong_per_600": 0.0,
      "strong_reference_cut_psnr": 42.755948066711426,
      "strong_reference_regression_count": 0,
      "true_vs_normal": 0.10282641410827636,
      "true_vs_shuffle": 0.09411616961161295,
      "true_vs_zero": 0.12258923530578614,
      "utility_mode": "max_dpsnr",
      "worst_count_le_-0.20": 0,
      "worst_per_600": 0.0
    },
    {
      "bank_name": "A0_L2_L3_L1_full",
      "chosen_action_counts": {
        "A0@0": 197,
        "L1_high_gain@1": 335,
        "L2_tail_safe@1": 43,
        "L3_balanced@1": 25
      },
      "chosen_variant_counts": {
        "A0": 197,
        "l1_fdf_lite_s004_g025_bm2": 335,
        "l2_fdf_lite_s002_g025_bm2": 43,
        "l3_fdf_lite_s004_g015_bm2": 25
      },
      "count": 600,
      "coverage": 1.0,
      "dSSIM": 2.1257599194844563e-05,
      "easy_top25_dPSNR": 0.1470032755533854,
      "fold": 0,
      "hard_bottom25_dPSNR": 0.09963709513346354,
      "intervention_rate": 0.6716666666666666,
      "mean_chosen_alpha": 0.6716666666666666,
      "mean_dPSNR": 0.123199888865153,
      "positive_ratio": 0.6716666666666666,
      "seed": 2026,
      "strong_count_le_-0.05": 0,
      "strong_per_600": 0.0,
      "strong_reference_cut_psnr": 42.755948066711426,
      "strong_reference_regression_count": 0,
      "true_vs_normal": 0.10229574521382649,
      "true_vs_shuffle": 0.09352704048156739,
      "true_vs_zero": 0.12208933194478352,
      "utility_mode": "tail_averse",
      "worst_count_le_-0.20": 0,
      "worst_per_600": 0.0
    },
    {
      "bank_name": "A0_L2_L3_L1_full",
      "chosen_action_counts": {
        "A0@0": 226,
        "L1_high_gain@1": 311,
        "L2_tail_safe@1": 39,
        "L3_balanced@1": 24
      },
      "chosen_variant_counts": {
        "A0": 226,
        "l1_fdf_lite_s004_g025_bm2": 311,
        "l2_fdf_lite_s002_g025_bm2": 39,
        "l3_fdf_lite_s004_g015_bm2": 24
      },
      "count": 600,
      "coverage": 1.0,
      "dSSIM": 2.4405022462209065e-05,
      "easy_top25_dPSNR": 0.1448504638671875,
      "fold": 0,
      "hard_bottom25_dPSNR": 0.0964013163248698,
      "intervention_rate": 0.6233333333333333,
      "mean_chosen_alpha": 0.6233333333333333,
      "mean_dPSNR": 0.1204759661356608,
      "positive_ratio": 0.6233333333333333,
      "seed": 2026,
      "strong_count_le_-0.05": 0,
      "strong_per_600": 0.0,
      "strong_reference_cut_psnr": 42.755948066711426,
      "strong_reference_regression_count": 0,
      "true_vs_normal": 0.09868829091389975,
      "true_vs_shuffle": 0.08976245562235514,
      "true_vs_zero": 0.11813520113627116,
      "utility_mode": "ssim_guarded",
      "worst_count_le_-0.20": 0,
      "worst_per_600": 0.0
    },
    {
      "bank_name": "A0_L2_L3_L1_shrink",
      "chosen_action_counts": {
        "A0@0": 175,
        "L1_high_gain@0.25": 8,
        "L1_high_gain@0.5": 7,
        "L1_high_gain@0.75": 4,
        "L1_high_gain@1": 333,
        "L2_tail_safe@0.25": 8,
        "L2_tail_safe@0.75": 3,
        "L2_tail_safe@1": 38,
        "L3_balanced@0.5": 1,
        "L3_balanced@0.75": 1,
        "L3_balanced@1": 22
      },
      "chosen_variant_counts": {
        "A0": 175,
        "l1_fdf_lite_s004_g025_bm2": 352,
        "l2_fdf_lite_s002_g025_bm2": 49,
        "l3_fdf_lite_s004_g015_bm2": 24
      },
      "count": 600,
      "coverage": 1.0,
      "dSSIM": 2.008060614267985e-05,
      "easy_top25_dPSNR": 0.14747159322102865,
      "fold": 0,
      "hard_bottom25_dPSNR": 0.10001899719238282,
      "intervention_rate": 0.7083333333333334,
      "mean_chosen_alpha": 0.6783333333333333,
      "mean_dPSNR": 0.12354255040486653,
      "positive_ratio": 0.7083333333333334,
      "seed": 2026,
      "strong_count_le_-0.05": 0,
      "strong_per_600": 0.0,
      "strong_reference_cut_psnr": 42.755948066711426,
      "strong_reference_regression_count": 0,
      "true_vs_normal": 0.10274343172709147,
      "true_vs_shuffle": 0.09419261614481608,
      "true_vs_zero": 0.12245813051859537,
      "utility_mode": "max_dpsnr",
      "worst_count_le_-0.20": 0,
      "worst_per_600": 0.0
    },
    {
      "bank_name": "A0_L2_L3_L1_shrink",
      "chosen_action_counts": {
        "A0@0": 179,
        "L1_high_gain@0.25": 8,
        "L1_high_gain@0.5": 6,
        "L1_high_gain@0.75": 4,
        "L1_high_gain@1": 328,
        "L2_tail_safe@0.25": 8,
        "L2_tail_safe@0.75": 4,
        "L2_tail_safe@1": 37,
        "L3_balanced@0.5": 1,
        "L3_balanced@0.75": 1,
        "L3_balanced@1": 24
      },
      "chosen_variant_counts": {
        "A0": 179,
        "l1_fdf_lite_s004_g025_bm2": 346,
        "l2_fdf_lite_s002_g025_bm2": 49,
        "l3_fdf_lite_s004_g015_bm2": 26
      },
      "count": 600,
      "coverage": 1.0,
      "dSSIM": 2.171635627746582e-05,
      "easy_top25_dPSNR": 0.14730712890625,
      "fold": 0,
      "hard_bottom25_dPSNR": 0.09966384887695312,
      "intervention_rate": 0.7016666666666667,
      "mean_chosen_alpha": 0.6720833333333334,
      "mean_dPSNR": 0.12337982813517252,
      "positive_ratio": 0.7016666666666667,
      "seed": 2026,
      "strong_count_le_-0.05": 0,
      "strong_per_600": 0.0,
      "strong_reference_cut_psnr": 42.755948066711426,
      "strong_reference_regression_count": 0,
      "true_vs_normal": 0.10234066963195801,
      "true_vs_shuffle": 0.0936734167734782,
      "true_vs_zero": 0.1219118849436442,
      "utility_mode": "tail_averse",
      "worst_count_le_-0.20": 0,
      "worst_per_600": 0.0
    },
    {
      "bank_name": "A0_L2_L3_L1_shrink",
      "chosen_action_counts": {
        "A0@0": 192,
        "L1_high_gain@0.25": 11,
        "L1_high_gain@0.5": 12,
        "L1_high_gain@0.75": 10,
        "L1_high_gain@1": 296,
        "L2_tail_safe@0.25": 9,
        "L2_tail_safe@0.5": 1,
        "L2_tail_safe@0.75": 4,
        "L2_tail_safe@1": 34,
        "L3_balanced@0.25": 5,
        "L3_balanced@0.5": 2,
        "L3_balanced@0.75": 2,
        "L3_balanced@1": 22
      },
      "chosen_variant_counts": {
        "A0": 192,
        "l1_fdf_lite_s004_g025_bm2": 329,
        "l2_fdf_lite_s002_g025_bm2": 48,
        "l3_fdf_lite_s004_g015_bm2": 31
      },
      "count": 600,
      "coverage": 1.0,
      "dSSIM": 2.463718255360921e-05,
      "easy_top25_dPSNR": 0.14464017232259116,
      "fold": 0,
      "hard_bottom25_dPSNR": 0.09654411315917968,
      "intervention_rate": 0.68,
      "mean_chosen_alpha": 0.6295833333333334,
      "mean_dPSNR": 0.12018688201904297,
      "positive_ratio": 0.68,
      "seed": 2026,
      "strong_count_le_-0.05": 0,
      "strong_per_600": 0.0,
      "strong_reference_cut_psnr": 42.755948066711426,
      "strong_reference_regression_count": 0,
      "true_vs_normal": 0.09802328109741211,
      "true_vs_shuffle": 0.08935659726460775,
      "true_vs_zero": 0.11710250536600748,
      "utility_mode": "ssim_guarded",
      "worst_count_le_-0.20": 0,
      "worst_per_600": 0.0
    },
    {
      "bank_name": "A0_L2_L3_L1_micro_shrink",
      "chosen_action_counts": {
        "A0@0": 170,
        "L1_high_gain@0.1": 5,
        "L1_high_gain@0.25": 6,
        "L1_high_gain@0.5": 7,
        "L1_high_gain@0.75": 4,
        "L1_high_gain@1": 333,
        "L2_tail_safe@0.1": 3,
        "L2_tail_safe@0.25": 7,
        "L2_tail_safe@0.75": 3,
        "L2_tail_safe@1": 38,
        "L3_balanced@0.5": 1,
        "L3_balanced@0.75": 1,
        "L3_balanced@1": 22
      },
      "chosen_variant_counts": {
        "A0": 170,
        "l1_fdf_lite_s004_g025_bm2": 355,
        "l2_fdf_lite_s002_g025_bm2": 51,
        "l3_fdf_lite_s004_g015_bm2": 24
      },
      "count": 600,
      "coverage": 1.0,
      "dSSIM": 2.011626958847046e-05,
      "easy_top25_dPSNR": 0.14748283386230468,
      "fold": 0,
      "hard_bottom25_dPSNR": 0.10001899719238282,
      "intervention_rate": 0.7166666666666667,
      "mean_chosen_alpha": 0.6784166666666667,
      "mean_dPSNR": 0.12354667027791341,
      "positive_ratio": 0.7166666666666667,
      "seed": 2026,
      "strong_count_le_-0.05": 0,
      "strong_per_600": 0.0,
      "strong_reference_cut_psnr": 42.755948066711426,
      "strong_reference_regression_count": 0,
      "true_vs_normal": 0.10265625953674316,
      "true_vs_shuffle": 0.09412887891133627,
      "true_vs_zero": 0.1223989454905192,
      "utility_mode": "max_dpsnr",
      "worst_count_le_-0.20": 0,
      "worst_per_600": 0.0
    },
    {
      "bank_name": "A0_L2_L3_L1_micro_shrink",
      "chosen_action_counts": {
        "A0@0": 173,
        "L1_high_gain@0.1": 5,
        "L1_high_gain@0.25": 7,
        "L1_high_gain@0.5": 6,
        "L1_high_gain@0.75": 4,
        "L1_high_gain@1": 328,
        "L2_tail_safe@0.1": 3,
        "L2_tail_safe@0.25": 7,
        "L2_tail_safe@0.75": 4,
        "L2_tail_safe@1": 37,
        "L3_balanced@0.5": 1,
        "L3_balanced@0.75": 1,
        "L3_balanced@1": 24
      },
      "chosen_variant_counts": {
        "A0": 173,
        "l1_fdf_lite_s004_g025_bm2": 350,
        "l2_fdf_lite_s002_g025_bm2": 51,
        "l3_fdf_lite_s004_g015_bm2": 26
      },
      "count": 600,
      "coverage": 1.0,
      "dSSIM": 2.1734337011973062e-05,
      "easy_top25_dPSNR": 0.1473200480143229,
      "fold": 0,
      "hard_bottom25_dPSNR": 0.09966384887695312,
      "intervention_rate": 0.7116666666666667,
      "mean_chosen_alpha": 0.6725833333333333,
      "mean_dPSNR": 0.12338436762491863,
      "positive_ratio": 0.7116666666666667,
      "seed": 2026,
      "strong_count_le_-0.05": 0,
      "strong_per_600": 0.0,
      "strong_reference_cut_psnr": 42.755948066711426,
      "strong_reference_regression_count": 0,
      "true_vs_normal": 0.10231127738952636,
      "true_vs_shuffle": 0.09367026964823405,
      "true_vs_zero": 0.1219290320078532,
      "utility_mode": "tail_averse",
      "worst_count_le_-0.20": 0,
      "worst_per_600": 0.0
    },
    {
      "bank_name": "A0_L2_L3_L1_micro_shrink",
      "chosen_action_counts": {
        "A0@0": 182,
        "L1_high_gain@0.1": 9,
        "L1_high_gain@0.25": 10,
        "L1_high_gain@0.5": 12,
        "L1_high_gain@0.75": 10,
        "L1_high_gain@1": 295,
        "L2_tail_safe@0.1": 4,
        "L2_tail_safe@0.25": 8,
        "L2_tail_safe@0.5": 1,
        "L2_tail_safe@0.75": 4,
        "L2_tail_safe@1": 34,
        "L3_balanced@0.25": 5,
        "L3_balanced@0.5": 2,
        "L3_balanced@0.75": 2,
        "L3_balanced@1": 22
      },
      "chosen_variant_counts": {
        "A0": 182,
        "l1_fdf_lite_s004_g025_bm2": 336,
        "l2_fdf_lite_s002_g025_bm2": 51,
        "l3_fdf_lite_s004_g015_bm2": 31
      },
      "count": 600,
      "coverage": 1.0,
      "dSSIM": 2.4718443552652994e-05,
      "easy_top25_dPSNR": 0.14468409220377604,
      "fold": 0,
      "hard_bottom25_dPSNR": 0.0966449228922526,
      "intervention_rate": 0.6966666666666667,
      "mean_chosen_alpha": 0.62925,
      "mean_dPSNR": 0.12008493423461913,
      "positive_ratio": 0.6966666666666667,
      "seed": 2026,
      "strong_count_le_-0.05": 0,
      "strong_per_600": 0.0,
      "strong_reference_cut_psnr": 42.755948066711426,
      "strong_reference_regression_count": 0,
      "true_vs_normal": 0.09794731775919596,
      "true_vs_shuffle": 0.08930399258931478,
      "true_vs_zero": 0.11700796445210775,
      "utility_mode": "ssim_guarded",
      "worst_count_le_-0.20": 0,
      "worst_per_600": 0.0
    },
    {
      "bank_name": "forced_L2_L3_L1_shrink_no_A0",
      "chosen_action_counts": {
        "L1_high_gain@0.25": 46,
        "L1_high_gain@0.5": 7,
        "L1_high_gain@0.75": 4,
        "L1_high_gain@1": 333,
        "L2_tail_safe@0.25": 142,
        "L2_tail_safe@0.75": 3,
        "L2_tail_safe@1": 38,
        "L3_balanced@0.25": 3,
        "L3_balanced@0.5": 1,
        "L3_balanced@0.75": 1,
        "L3_balanced@1": 22
      },
      "chosen_variant_counts": {
        "l1_fdf_lite_s004_g025_bm2": 390,
        "l2_fdf_lite_s002_g025_bm2": 183,
        "l3_fdf_lite_s004_g015_bm2": 27
      },
      "count": 600,
      "coverage": 1.0,
      "dSSIM": 1.8274982770284018e-05,
      "easy_top25_dPSNR": 0.1367656453450521,
      "fold": 0,
      "hard_bottom25_dPSNR": 0.09260622660319011,
      "intervention_rate": 1.0,
      "mean_chosen_alpha": 0.75125,
      "mean_dPSNR": 0.11405476252237956,
      "positive_ratio": 0.7083333333333334,
      "seed": 2026,
      "strong_count_le_-0.05": 40,
      "strong_per_600": 40.0,
      "strong_reference_cut_psnr": 42.755948066711426,
      "strong_reference_regression_count": 13,
      "true_vs_normal": 0.09936450004577636,
      "true_vs_shuffle": 0.09153519630432129,
      "true_vs_zero": 0.11799689610799154,
      "utility_mode": "max_dpsnr",
      "worst_count_le_-0.20": 0,
      "worst_per_600": 0.0
    },
    {
      "bank_name": "forced_L2_L3_L1_shrink_no_A0",
      "chosen_action_counts": {
        "L1_high_gain@0.25": 46,
        "L1_high_gain@0.5": 6,
        "L1_high_gain@0.75": 4,
        "L1_high_gain@1": 328,
        "L2_tail_safe@0.25": 142,
        "L2_tail_safe@0.75": 4,
        "L2_tail_safe@1": 37,
        "L3_balanced@0.25": 7,
        "L3_balanced@0.5": 1,
        "L3_balanced@0.75": 1,
        "L3_balanced@1": 24
      },
      "chosen_variant_counts": {
        "l1_fdf_lite_s004_g025_bm2": 384,
        "l2_fdf_lite_s002_g025_bm2": 183,
        "l3_fdf_lite_s004_g015_bm2": 33
      },
      "count": 600,
      "coverage": 1.0,
      "dSSIM": 1.968661944071452e-05,
      "easy_top25_dPSNR": 0.13660980224609376,
      "fold": 0,
      "hard_bottom25_dPSNR": 0.09233591715494792,
      "intervention_rate": 1.0,
      "mean_chosen_alpha": 0.7466666666666667,
      "mean_dPSNR": 0.11391018549601237,
      "positive_ratio": 0.7066666666666667,
      "seed": 2026,
      "strong_count_le_-0.05": 40,
      "strong_per_600": 40.0,
      "strong_reference_cut_psnr": 42.755948066711426,
      "strong_reference_regression_count": 13,
      "true_vs_normal": 0.09900259335835775,
      "true_vs_shuffle": 0.09108758608500163,
      "true_vs_zero": 0.11755617141723633,
      "utility_mode": "tail_averse",
      "worst_count_le_-0.20": 0,
      "worst_per_600": 0.0
    },
    {
      "bank_name": "forced_L2_L3_L1_shrink_no_A0",
      "chosen_action_counts": {
        "L1_high_gain@0.25": 50,
        "L1_high_gain@0.5": 13,
        "L1_high_gain@0.75": 11,
        "L1_high_gain@1": 304,
        "L2_tail_safe@0.25": 143,
        "L2_tail_safe@0.5": 1,
        "L2_tail_safe@0.75": 5,
        "L2_tail_safe@1": 35,
        "L3_balanced@0.25": 10,
        "L3_balanced@0.5": 2,
        "L3_balanced@0.75": 2,
        "L3_balanced@1": 24
      },
      "chosen_variant_counts": {
        "l1_fdf_lite_s004_g025_bm2": 378,
        "l2_fdf_lite_s002_g025_bm2": 184,
        "l3_fdf_lite_s004_g015_bm2": 38
      },
      "count": 600,
      "coverage": 1.0,
      "dSSIM": 1.940945784250895e-05,
      "easy_top25_dPSNR": 0.13498570760091147,
      "fold": 0,
      "hard_bottom25_dPSNR": 0.09178609212239583,
      "intervention_rate": 1.0,
      "mean_chosen_alpha": 0.7254166666666667,
      "mean_dPSNR": 0.11196282068888347,
      "positive_ratio": 0.7083333333333334,
      "seed": 2026,
      "strong_count_le_-0.05": 40,
      "strong_per_600": 40.0,
      "strong_reference_cut_psnr": 42.755948066711426,
      "strong_reference_regression_count": 13,
      "true_vs_normal": 0.09652555147806803,
      "true_vs_shuffle": 0.08864144961039225,
      "true_vs_zero": 0.11504313786824544,
      "utility_mode": "ssim_guarded",
      "worst_count_le_-0.20": 0,
      "worst_per_600": 0.0
    }
  ],
  "candidate_checkpoints": {
    "l1_fdf_lite_s004_g025_bm2": "/sda/home/wangyuxin/ConvIR-B/repos/ConvIR-B-dta-v3-6-hrcs/Dehazing/ITS/results/ConvIR-Haze4K-DTA-v3-5-FDF-RCS-l1_fdf_lite_s004_g025_bm2-seed2026_f0-quick5full/Training-Results/Final.pkl",
    "l2_fdf_lite_s002_g025_bm2": "/sda/home/wangyuxin/ConvIR-B/repos/ConvIR-B-dta-v3-6-hrcs/Dehazing/ITS/results/ConvIR-Haze4K-DTA-v3-5-FDF-RCS-l2_fdf_lite_s002_g025_bm2-seed2026_f0-quick5full/Training-Results/Final.pkl",
    "l3_fdf_lite_s004_g015_bm2": "/sda/home/wangyuxin/ConvIR-B/repos/ConvIR-B-dta-v3-6-hrcs/Dehazing/ITS/results/ConvIR-Haze4K-DTA-v3-5-FDF-RCS-l3_fdf_lite_s004_g015_bm2-seed2026_f0-quick5full/Training-Results/Final.pkl"
  },
  "count_images": 600,
  "elapsed_sec": 348.83467149734497,
  "fold": 0,
  "locked_test_touched": false,
  "peak_cuda_mem_mib": 1118.55517578125,
  "phase": "C1_real_soft_blend_group",
  "route": "DTA-v3.7 U-TQS-Mix",
  "seed": 2026,
  "selected_csv": "/sda/home/wangyuxin/ConvIR-B/repos/ConvIR-B-dta-v3-7-u-tqs-mix-phasec1/experience_docx/experiment_logs/haze4k_dta_v3_7_u_tqs_mix_20260613/phase_c1_real_blend_groups/v37_real_blend_selected_seed2026_f0.csv",
  "selected_rows": 10800,
  "single_action_csv": "/sda/home/wangyuxin/ConvIR-B/repos/ConvIR-B-dta-v3-7-u-tqs-mix-phasec1/experience_docx/experiment_logs/haze4k_dta_v3_7_u_tqs_mix_20260613/phase_c1_real_blend_groups/v37_real_blend_single_actions_seed2026_f0.csv",
  "single_action_metrics": [
    {
      "action": "L1_high_gain@0.1",
      "count": 600,
      "coverage": 1.0,
      "dSSIM": 2.0102659861246745e-06,
      "easy_top25_dPSNR": 0.011294657389322917,
      "fold": 0,
      "hard_bottom25_dPSNR": 0.00635955810546875,
      "mean_dPSNR": 0.008411006927490234,
      "positive_ratio": 0.6966666666666667,
      "seed": 2026,
      "strong_count_le_-0.05": 7,
      "strong_per_600": 7.0,
      "strong_reference_cut_psnr": 42.755948066711426,
      "strong_reference_regression_count": 4,
      "true_vs_normal": 0.00868690808614095,
      "true_vs_shuffle": 0.008220860163370768,
      "true_vs_zero": 0.010406440099080403,
      "worst_count_le_-0.20": 0,
      "worst_per_600": 0.0
    },
    {
      "action": "L1_high_gain@0.25",
      "count": 600,
      "coverage": 1.0,
      "dSSIM": 4.424750804901123e-06,
      "easy_top25_dPSNR": 0.02618695576985677,
      "fold": 0,
      "hard_bottom25_dPSNR": 0.015756060282389323,
      "mean_dPSNR": 0.020139557520548503,
      "positive_ratio": 0.6816666666666666,
      "seed": 2026,
      "strong_count_le_-0.05": 68,
      "strong_per_600": 68.0,
      "strong_reference_cut_psnr": 42.755948066711426,
      "strong_reference_regression_count": 22,
      "true_vs_normal": 0.02121028264363607,
      "true_vs_shuffle": 0.020073172251383463,
      "true_vs_zero": 0.025438226064046224,
      "worst_count_le_-0.20": 0,
      "worst_per_600": 0.0
    },
    {
      "action": "L1_high_gain@0.5",
      "count": 600,
      "coverage": 1.0,
      "dSSIM": 6.9241722424825034e-06,
      "easy_top25_dPSNR": 0.045460357666015624,
      "fold": 0,
      "hard_bottom25_dPSNR": 0.031030667622884114,
      "mean_dPSNR": 0.03728746732076009,
      "positive_ratio": 0.675,
      "seed": 2026,
      "strong_count_le_-0.05": 116,
      "strong_per_600": 116.0,
      "strong_reference_cut_psnr": 42.755948066711426,
      "strong_reference_regression_count": 35,
      "true_vs_normal": 0.04070258140563965,
      "true_vs_shuffle": 0.038523314793904626,
      "true_vs_zero": 0.048917748133341474,
      "worst_count_le_-0.20": 12,
      "worst_per_600": 12.0
    },
    {
      "action": "L1_high_gain@0.75",
      "count": 600,
      "coverage": 1.0,
      "dSSIM": 7.475713888804118e-06,
      "easy_top25_dPSNR": 0.05769037882486979,
      "fold": 0,
      "hard_bottom25_dPSNR": 0.04581862131754557,
      "mean_dPSNR": 0.05139141400655111,
      "positive_ratio": 0.6616666666666666,
      "seed": 2026,
      "strong_count_le_-0.05": 148,
      "strong_per_600": 148.0,
      "strong_reference_cut_psnr": 42.755948066711426,
      "strong_reference_regression_count": 42,
      "true_vs_normal": 0.058429384231567384,
      "true_vs_shuffle": 0.055304953257242835,
      "true_vs_zero": 0.07038439432779948,
      "worst_count_le_-0.20": 44,
      "worst_per_600": 44.0
    },
    {
      "action": "L1_high_gain@1",
      "count": 600,
      "coverage": 1.0,
      "dSSIM": 6.10580046971639e-06,
      "easy_top25_dPSNR": 0.06278345743815104,
      "fold": 0,
      "hard_bottom25_dPSNR": 0.06011357625325521,
      "mean_dPSNR": 0.06240987777709961,
      "positive_ratio": 0.6533333333333333,
      "seed": 2026,
      "strong_count_le_-0.05": 159,
      "strong_per_600": 159.0,
      "strong_reference_cut_psnr": 42.755948066711426,
      "strong_reference_regression_count": 48,
      "true_vs_normal": 0.07435043652852376,
      "true_vs_shuffle": 0.07038052558898926,
      "true_vs_zero": 0.08979269663492838,
      "worst_count_le_-0.20": 72,
      "worst_per_600": 72.0
    },
    {
      "action": "L2_tail_safe@0.1",
      "count": 600,
      "coverage": 1.0,
      "dSSIM": 1.6439954439798991e-06,
      "easy_top25_dPSNR": 0.00750335693359375,
      "fold": 0,
      "hard_bottom25_dPSNR": 0.003951403299967448,
      "mean_dPSNR": 0.005060892105102539,
      "positive_ratio": 0.66,
      "seed": 2026,
      "strong_count_le_-0.05": 1,
      "strong_per_600": 1.0,
      "strong_reference_cut_psnr": 42.755948066711426,
      "strong_reference_regression_count": 0,
      "true_vs_normal": 0.005555543899536133,
      "true_vs_shuffle": 0.005297934214274089,
      "true_vs_zero": 0.007041012446085612,
      "worst_count_le_-0.20": 0,
      "worst_per_600": 0.0
    },
    {
      "action": "L2_tail_safe@0.25",
      "count": 600,
      "coverage": 1.0,
      "dSSIM": 3.658135732014974e-06,
      "easy_top25_dPSNR": 0.017554092407226562,
      "fold": 0,
      "hard_bottom25_dPSNR": 0.009768880208333334,
      "mean_dPSNR": 0.012106240590413412,
      "positive_ratio": 0.655,
      "seed": 2026,
      "strong_count_le_-0.05": 41,
      "strong_per_600": 41.0,
      "strong_reference_cut_psnr": 42.755948066711426,
      "strong_reference_regression_count": 13,
      "true_vs_normal": 0.013660812377929687,
      "true_vs_shuffle": 0.013024730682373047,
      "true_vs_zero": 0.017299079895019533,
      "worst_count_le_-0.20": 0,
      "worst_per_600": 0.0
    },
    {
      "action": "L2_tail_safe@0.5",
      "count": 600,
      "coverage": 1.0,
      "dSSIM": 5.98450501759847e-06,
      "easy_top25_dPSNR": 0.031055196126302084,
      "fold": 0,
      "hard_bottom25_dPSNR": 0.019171892801920574,
      "mean_dPSNR": 0.022379134496053058,
      "positive_ratio": 0.645,
      "seed": 2026,
      "strong_count_le_-0.05": 95,
      "strong_per_600": 95.0,
      "strong_reference_cut_psnr": 42.755948066711426,
      "strong_reference_regression_count": 24,
      "true_vs_normal": 0.02655078887939453,
      "true_vs_shuffle": 0.0253057861328125,
      "true_vs_zero": 0.03357334772745768,
      "worst_count_le_-0.20": 4,
      "worst_per_600": 4.0
    },
    {
      "action": "L2_tail_safe@0.75",
      "count": 600,
      "coverage": 1.0,
      "dSSIM": 6.953279177347819e-06,
      "easy_top25_dPSNR": 0.04044509887695313,
      "fold": 0,
      "hard_bottom25_dPSNR": 0.028207537333170572,
      "mean_dPSNR": 0.03079707145690918,
      "positive_ratio": 0.6316666666666667,
      "seed": 2026,
      "strong_count_le_-0.05": 135,
      "strong_per_600": 135.0,
      "strong_reference_cut_psnr": 42.755948066711426,
      "strong_reference_regression_count": 35,
      "true_vs_normal": 0.038651323318481444,
      "true_vs_shuffle": 0.03682647069295247,
      "true_vs_zero": 0.04880068461100261,
      "worst_count_le_-0.20": 22,
      "worst_per_600": 22.0
    },
    {
      "action": "L2_tail_safe@1",
      "count": 600,
      "coverage": 1.0,
      "dSSIM": 6.583631038665771e-06,
      "easy_top25_dPSNR": 0.0456854248046875,
      "fold": 0,
      "hard_bottom25_dPSNR": 0.03687305450439453,
      "mean_dPSNR": 0.037343956629435224,
      "positive_ratio": 0.6266666666666667,
      "seed": 2026,
      "strong_count_le_-0.05": 154,
      "strong_per_600": 154.0,
      "strong_reference_cut_psnr": 42.755948066711426,
      "strong_reference_regression_count": 40,
      "true_vs_normal": 0.04994629859924316,
      "true_vs_shuffle": 0.0475718879699707,
      "true_vs_zero": 0.06296159744262696,
      "worst_count_le_-0.20": 46,
      "worst_per_600": 46.0
    },
    {
      "action": "L3_balanced@0.1",
      "count": 600,
      "coverage": 1.0,
      "dSSIM": 1.9482771555582683e-06,
      "easy_top25_dPSNR": 0.009294586181640625,
      "fold": 0,
      "hard_bottom25_dPSNR": 0.005249341328938802,
      "mean_dPSNR": 0.00672972043355306,
      "positive_ratio": 0.68,
      "seed": 2026,
      "strong_count_le_-0.05": 4,
      "strong_per_600": 4.0,
      "strong_reference_cut_psnr": 42.755948066711426,
      "strong_reference_regression_count": 1,
      "true_vs_normal": 0.00690974235534668,
      "true_vs_shuffle": 0.006569677988688151,
      "true_vs_zero": 0.008516343434651692,
      "worst_count_le_-0.20": 0,
      "worst_per_600": 0.0
    },
    {
      "action": "L3_balanced@0.25",
      "count": 600,
      "coverage": 1.0,
      "dSSIM": 4.362265268961589e-06,
      "easy_top25_dPSNR": 0.021672948201497396,
      "fold": 0,
      "hard_bottom25_dPSNR": 0.012998390197753906,
      "mean_dPSNR": 0.01613200823465983,
      "positive_ratio": 0.6733333333333333,
      "seed": 2026,
      "strong_count_le_-0.05": 53,
      "strong_per_600": 53.0,
      "strong_reference_cut_psnr": 42.755948066711426,
      "strong_reference_regression_count": 19,
      "true_vs_normal": 0.016928653717041015,
      "true_vs_shuffle": 0.01609440803527832,
      "true_vs_zero": 0.02086160977681478,
      "worst_count_le_-0.20": 0,
      "worst_per_600": 0.0
    },
    {
      "action": "L3_balanced@0.5",
      "count": 600,
      "coverage": 1.0,
      "dSSIM": 7.090667883555095e-06,
      "easy_top25_dPSNR": 0.038079503377278646,
      "fold": 0,
      "hard_bottom25_dPSNR": 0.025578816731770832,
      "mean_dPSNR": 0.029935652414957683,
      "positive_ratio": 0.6633333333333333,
      "seed": 2026,
      "strong_count_le_-0.05": 108,
      "strong_per_600": 108.0,
      "strong_reference_cut_psnr": 42.755948066711426,
      "strong_reference_regression_count": 30,
      "true_vs_normal": 0.03268588066101074,
      "true_vs_shuffle": 0.03107282002766927,
      "true_vs_zero": 0.04027146657307943,
      "worst_count_le_-0.20": 8,
      "worst_per_600": 8.0
    },
    {
      "action": "L3_balanced@0.75",
      "count": 600,
      "coverage": 1.0,
      "dSSIM": 8.172293504079182e-06,
      "easy_top25_dPSNR": 0.0491345469156901,
      "fold": 0,
      "hard_bottom25_dPSNR": 0.03773675282796224,
      "mean_dPSNR": 0.041377166112264,
      "positive_ratio": 0.66,
      "seed": 2026,
      "strong_count_le_-0.05": 135,
      "strong_per_600": 135.0,
      "strong_reference_cut_psnr": 42.755948066711426,
      "strong_reference_regression_count": 38,
      "true_vs_normal": 0.04724240303039551,
      "true_vs_shuffle": 0.04490737597147624,
      "true_vs_zero": 0.05819477081298828,
      "worst_count_le_-0.20": 31,
      "worst_per_600": 31.0
    },
    {
      "action": "L3_balanced@1",
      "count": 600,
      "coverage": 1.0,
      "dSSIM": 7.599095503489176e-06,
      "easy_top25_dPSNR": 0.054778366088867186,
      "fold": 0,
      "hard_bottom25_dPSNR": 0.04946862538655599,
      "mean_dPSNR": 0.050430129369099935,
      "positive_ratio": 0.65,
      "seed": 2026,
      "strong_count_le_-0.05": 155,
      "strong_per_600": 155.0,
      "strong_reference_cut_psnr": 42.755948066711426,
      "strong_reference_regression_count": 43,
      "true_vs_normal": 0.06057356516520182,
      "true_vs_shuffle": 0.057575098673502606,
      "true_vs_zero": 0.07460231781005859,
      "worst_count_le_-0.20": 56,
      "worst_per_600": 56.0
    }
  ],
  "single_action_rows": 9000,
  "split_name": "fold0_val"
}
