{
  "action_alphas": [
    0.0,
    0.125,
    0.25,
    0.375,
    0.5,
    0.75
  ],
  "alphas": [
    0.125,
    0.25,
    0.375,
    0.5,
    0.75
  ],
  "best_formal_in_sample_policy": null,
  "best_in_sample_policy": {
    "action_count_a0": 90,
    "action_count_a0p125": 0,
    "action_count_a0p25": 420,
    "action_count_a0p375": 0,
    "action_count_a0p5": 0,
    "action_count_a0p75": 90,
    "action_fraction_a0": 0.15,
    "action_fraction_a0p125": 0.0,
    "action_fraction_a0p25": 0.7,
    "action_fraction_a0p375": 0.0,
    "action_fraction_a0p5": 0.0,
    "action_fraction_a0p75": 0.15,
    "complexity": 2,
    "count": 600,
    "coverage": 0.85,
    "dSSIM": 0.0002802250782648722,
    "easy_top25_dPSNR": 0.42092918395996093,
    "formal_candidate_gate_pass": false,
    "hard_bottom25_dPSNR": 0.5204439798990885,
    "mean_dPSNR": 0.44969295501708983,
    "nonnegative_ratio": 0.8333333333333334,
    "policy_id": "tier|low_alpha=0.25|low_cond=diff_signed_mean_le_0.0027975643|high_alpha=0.75|high_cond=diff_signed_mean_le_-0.0045283467",
    "positive_ratio": 0.6833333333333333,
    "score": 1.1643371357637295,
    "screen_gate_pass": false,
    "selected_count": 510,
    "selected_nonnegative_ratio": 0.803921568627451,
    "selected_precision": 0.803921568627451,
    "selected_severe_count": 46,
    "severe_loss_count": 46,
    "severe_loss_per_600": 46.0,
    "strong_loss_count": 85,
    "strong_loss_per_600": 85.0
  },
  "best_screen_in_sample_policy": null,
  "c6_decision": "C6_MULTIALPHA_OOF_SCREEN_PASS_STRONG_TARGET_NOT_YET_START_C7_C8",
  "c6_formal_candidate_gate": {
    "dSSIM": 0.0,
    "easy_top25_dPSNR": 0.0,
    "hard_bottom25_dPSNR": 0.3,
    "mean_dPSNR": 0.2,
    "positive_ratio": 0.7,
    "severe_loss_per_600": 48.0
  },
  "c6_screen_gate": {
    "dSSIM": 0.0,
    "easy_top25_dPSNR": 0.0,
    "hard_bottom25_dPSNR": 0.28,
    "mean_dPSNR": 0.2,
    "positive_ratio": 0.69,
    "severe_loss_per_600": 48.0
  },
  "c7_decision": "C7_PATCH_ALPHA_ORACLE_STRONG_SIGNAL_START_LOCAL_ALPHA",
  "c7_patch_signal_gate": {
    "dSSIM": 0.0,
    "hard_bottom25_dPSNR": 0.35,
    "positive_ratio": 0.72
  },
  "decision": "C6_MULTIALPHA_OOF_SCREEN_PASS_STRONG_TARGET_NOT_YET_START_C7_C8__C7_PATCH_ALPHA_ORACLE_STRONG_SIGNAL_START_LOCAL_ALPHA",
  "fold_rows": [
    {
      "count": 136,
      "coverage": 0.9191176470588235,
      "dSSIM": 0.00026227752952014696,
      "easy_top25_dPSNR": 0.6308293062097886,
      "fold": 0,
      "formal_candidate_gate_pass": true,
      "hard_bottom25_dPSNR": 0.4722124548519359,
      "heldout_count": 136,
      "mean_dPSNR": 0.43392449266770305,
      "nonnegative_ratio": 0.8161764705882353,
      "positive_ratio": 0.7352941176470589,
      "score": 1.184997975405525,
      "screen_gate_pass": true,
      "selected_count": 125,
      "selected_nonnegative_ratio": 0.8,
      "selected_precision": 0.8,
      "selected_severe_count": 10,
      "severe_loss_count": 10,
      "severe_loss_per_600": 44.11764705882353,
      "strong_loss_count": 20,
      "strong_loss_per_600": 88.23529411764706,
      "train_count": 464,
      "train_formal_candidate_gate_pass": true,
      "train_policy_id": "tier|low_alpha=0.25|low_cond=diff_signed_mean_le_0.0041439879|high_alpha=0.75|high_cond=diff_signed_mean_le_-0.0068474563",
      "train_score": 1.0988785976587983,
      "train_screen_gate_pass": true
    },
    {
      "count": 115,
      "coverage": 0.8956521739130435,
      "dSSIM": 0.00021588802337646484,
      "easy_top25_dPSNR": 0.3987245559692383,
      "fold": 1,
      "formal_candidate_gate_pass": true,
      "hard_bottom25_dPSNR": 0.476705687386649,
      "heldout_count": 115,
      "mean_dPSNR": 0.3833963808806046,
      "nonnegative_ratio": 0.808695652173913,
      "positive_ratio": 0.7043478260869566,
      "score": 1.1147363834320148,
      "screen_gate_pass": true,
      "selected_count": 103,
      "selected_nonnegative_ratio": 0.7864077669902912,
      "selected_precision": 0.7864077669902912,
      "selected_severe_count": 7,
      "severe_loss_count": 7,
      "severe_loss_per_600": 36.52173913043478,
      "strong_loss_count": 19,
      "strong_loss_per_600": 99.13043478260869,
      "train_count": 485,
      "train_formal_candidate_gate_pass": false,
      "train_policy_id": "tier|low_alpha=0.25|low_cond=diff_signed_mean_le_0.0030439693|high_alpha=0.75|high_cond=diff_signed_mean_le_-0.0073640332",
      "train_score": 1.1088869367155838,
      "train_screen_gate_pass": true
    },
    {
      "count": 116,
      "coverage": 0.8189655172413793,
      "dSSIM": 0.0003134341075502593,
      "easy_top25_dPSNR": 0.40512374351764546,
      "fold": 2,
      "formal_candidate_gate_pass": false,
      "hard_bottom25_dPSNR": 0.8097632177944841,
      "heldout_count": 116,
      "mean_dPSNR": 0.5348027821244865,
      "nonnegative_ratio": 0.8620689655172413,
      "positive_ratio": 0.6810344827586207,
      "score": 1.474187436700949,
      "screen_gate_pass": false,
      "selected_count": 95,
      "selected_nonnegative_ratio": 0.8315789473684211,
      "selected_precision": 0.8315789473684211,
      "selected_severe_count": 9,
      "severe_loss_count": 9,
      "severe_loss_per_600": 46.55172413793104,
      "strong_loss_count": 13,
      "strong_loss_per_600": 67.24137931034483,
      "train_count": 484,
      "train_formal_candidate_gate_pass": false,
      "train_policy_id": "tier|low_alpha=0.25|low_cond=diff_signed_mean_le_0.0027345826|high_alpha=0.75|high_cond=diff_signed_mean_le_-0.0044290172",
      "train_score": 1.1076471564727126,
      "train_screen_gate_pass": false
    },
    {
      "count": 111,
      "coverage": 0.8648648648648649,
      "dSSIM": 0.0002881422773137823,
      "easy_top25_dPSNR": 0.5115572611490885,
      "fold": 3,
      "formal_candidate_gate_pass": false,
      "hard_bottom25_dPSNR": 0.5936201590078848,
      "heldout_count": 111,
      "mean_dPSNR": 0.36908027717659064,
      "nonnegative_ratio": 0.8288288288288288,
      "positive_ratio": 0.6936936936936937,
      "score": 1.1773984593266364,
      "screen_gate_pass": true,
      "selected_count": 96,
      "selected_nonnegative_ratio": 0.8020833333333334,
      "selected_precision": 0.8020833333333334,
      "selected_severe_count": 8,
      "severe_loss_count": 8,
      "severe_loss_per_600": 43.24324324324324,
      "strong_loss_count": 15,
      "strong_loss_per_600": 81.08108108108108,
      "train_count": 489,
      "train_formal_candidate_gate_pass": false,
      "train_policy_id": "tier|low_alpha=0.25|low_cond=diff_signed_mean_le_0.0028705212|high_alpha=0.75|high_cond=diff_signed_mean_le_-0.0045321998",
      "train_score": 1.1738359419017337,
      "train_screen_gate_pass": false
    },
    {
      "count": 122,
      "coverage": 0.8688524590163934,
      "dSSIM": 0.0002976152740541052,
      "easy_top25_dPSNR": 0.42599817911783855,
      "fold": 4,
      "formal_candidate_gate_pass": false,
      "hard_bottom25_dPSNR": 0.21239363352457682,
      "heldout_count": 122,
      "mean_dPSNR": 0.39011512818883676,
      "nonnegative_ratio": 0.8032786885245902,
      "positive_ratio": 0.6721311475409836,
      "score": 0.5246209554163891,
      "screen_gate_pass": false,
      "selected_count": 106,
      "selected_nonnegative_ratio": 0.7735849056603774,
      "selected_precision": 0.7735849056603774,
      "selected_severe_count": 12,
      "severe_loss_count": 12,
      "severe_loss_per_600": 59.01639344262295,
      "strong_loss_count": 22,
      "strong_loss_per_600": 108.19672131147541,
      "train_count": 478,
      "train_formal_candidate_gate_pass": true,
      "train_policy_id": "tier|low_alpha=0.25|low_cond=diff_signed_mean_le_0.0038177745|high_alpha=0.75|high_cond=diff_signed_mean_le_-0.0053551169",
      "train_score": 1.2072358815720428,
      "train_screen_gate_pass": true
    }
  ],
  "image_multialpha_oracle_summary": {
    "count": 600,
    "coverage": 0.7966666666666666,
    "dSSIM": 0.0004145186146100362,
    "easy_top25_dPSNR": 0.8317298380533854,
    "formal_candidate_gate_pass": true,
    "hard_bottom25_dPSNR": 0.9266457621256511,
    "mean_dPSNR": 0.8288999875386556,
    "nonnegative_ratio": 1.0,
    "positive_ratio": 0.7966666666666666,
    "score": 2.085789581044515,
    "screen_gate_pass": true,
    "selected_count": 478,
    "selected_nonnegative_ratio": 1.0,
    "selected_precision": 1.0,
    "selected_severe_count": 0,
    "severe_loss_count": 0,
    "severe_loss_per_600": 0.0,
    "strong_loss_count": 0,
    "strong_loss_per_600": 0.0
  },
  "locked_test_touched": false,
  "meta": {
    "a0_checkpoint": "/sda/home/wangyuxin/ConvIR-B/checkpoints/official/Haze4K/haze4k-base.pkl",
    "a0_sha256": "6f42037d57a4e3de3a10ac0ab909d66a3415864a19433c29204a975f4efa4088",
    "alphas": [
      0.125,
      0.25,
      0.375,
      0.5,
      0.75
    ],
    "depth_normalization": "per_image_minmax_to_udpnet_depth2l_contract",
    "device": "cuda",
    "elapsed_sec": 74.17710423469543,
    "locked_test_touched": false,
    "official_checkpoint": "/sda/home/wangyuxin/ConvIR-B/checkpoints/udpnet/ConvIR_UDPNet_haze4k.ckpt",
    "official_checkpoint_meta": {
      "epoch": 1265,
      "global_step": 272190,
      "pytorch_lightning_version": "2.3.1",
      "state_dict_key_count": 689
    },
    "official_sha256": "6d02d2a42e97cc411a36d95cfaf8421eb25a5622f0cac8c150c0e790b7149291",
    "patch_sizes": [
      128
    ],
    "split_json": "/sda/home/wangyuxin/ConvIR-B/repos/ConvIR-B-v21-segmix-multialpha-local/experience_docx/experiment_logs/haze4k_dpga_v13_hsdf_20260604/internal_val/haze4k_dpga_v13_regular_hard_seed3407.json",
    "splits": [
      "val_regular",
      "val_hard"
    ],
    "udp_repo": "/sda/home/wangyuxin/ConvIR-B/repos/UDPNet"
  },
  "oof_summary": {
    "count": 600,
    "coverage": 0.875,
    "dSSIM": 0.000275246798992157,
    "easy_top25_dPSNR": 0.44730450948079425,
    "formal_candidate_gate_pass": false,
    "hard_bottom25_dPSNR": 0.479300422668457,
    "mean_dPSNR": 0.42283898989359536,
    "nonnegative_ratio": 0.8233333333333334,
    "positive_ratio": 0.6983333333333334,
    "score": 1.1369145408812025,
    "screen_gate_pass": true,
    "selected_count": 525,
    "selected_nonnegative_ratio": 0.7980952380952381,
    "selected_precision": 0.7980952380952381,
    "selected_severe_count": 46,
    "severe_loss_count": 46,
    "severe_loss_per_600": 46.0,
    "strong_loss_count": 89,
    "strong_loss_per_600": 89.0
  },
  "patch_summary_rows": [
    {
      "count": 600,
      "coverage": 0.995,
      "dSSIM": 0.0005613898237546284,
      "easy_top25_dPSNR": 1.27568598429362,
      "hard_bottom25_dPSNR": 1.1079598617553712,
      "mean_dPSNR": 1.1609541734059652,
      "mean_selected_patch_fraction": 0.7109166666666666,
      "nonnegative_ratio": 1.0,
      "patch_signal_gate_pass": true,
      "patch_size": 128,
      "patch_variant": "oracle_max",
      "positive_ratio": 0.995,
      "selected_count": 597,
      "selected_nonnegative_ratio": 1.0,
      "selected_precision": 1.0,
      "selected_severe_count": 0,
      "severe_loss_count": 0,
      "severe_loss_per_600": 0.0,
      "strong_loss_count": 0,
      "strong_loss_per_600": 0.0
    },
    {
      "count": 600,
      "coverage": 0.995,
      "dSSIM": 0.0004885443051656088,
      "easy_top25_dPSNR": 1.066505864461263,
      "hard_bottom25_dPSNR": 0.7569832992553711,
      "mean_dPSNR": 0.8769231764475505,
      "mean_selected_patch_fraction": 0.7109166666666666,
      "nonnegative_ratio": 1.0,
      "patch_signal_gate_pass": true,
      "patch_size": 128,
      "patch_variant": "oracle_riskcap0p5",
      "positive_ratio": 0.995,
      "selected_count": 597,
      "selected_nonnegative_ratio": 1.0,
      "selected_precision": 1.0,
      "selected_severe_count": 0,
      "severe_loss_count": 0,
      "severe_loss_per_600": 0.0,
      "strong_loss_count": 0,
      "strong_loss_per_600": 0.0
    }
  ],
  "phase": "C6 Multi-Alpha OOF Router + C7 Patch-Alpha Oracle",
  "route": "Haze4K-v2.1 SEG-Mix"
}
