{
  "action_rows": 27000,
  "feature_note": "Threshold selector uses only per-image diagnostics from train-derived OOF folds; locked test is untouched.",
  "locked_test_touched": false,
  "max_coverage": 0.95,
  "min_coverage": 0.2,
  "protocol": "nested_fold_threshold_selector_relaxed_flow",
  "reports": [
    {
      "all_image_positive_ratio": 0.12611111111111112,
      "calibration_coverage": 0.2,
      "calibration_objective": -0.13277844636175368,
      "coverage": 0.19333333333333333,
      "direction": ">=",
      "feature": "input_brightness_mean",
      "inner_calibration_fold": "1,2,3,4",
      "outer_fold": "0",
      "selected_dssim": 1.5326672130160861e-06,
      "selected_hard": 0.03270313262939453,
      "selected_mean": 0.010470923317803277,
      "selected_positive_ratio": 0.6522988505747126,
      "threshold": 0.6487957954406738,
      "true_vs_normal": 0.012193368275960287,
      "true_vs_shuffle": 0.011467429267035591,
      "true_vs_zero": 0.015121208826700845,
      "variant": "l1_fdf_lite_s004_g025_bm2",
      "worst": 37
    },
    {
      "all_image_positive_ratio": 0.11222222222222222,
      "calibration_coverage": 0.2,
      "calibration_objective": -0.14692244993845624,
      "coverage": 0.17666666666666667,
      "direction": ">=",
      "feature": "input_brightness_mean",
      "inner_calibration_fold": "0,2,3,4",
      "outer_fold": "1",
      "selected_dssim": 1.8488036261664496e-06,
      "selected_hard": 0.018622940911187064,
      "selected_mean": 0.01216738912794325,
      "selected_positive_ratio": 0.6352201257861635,
      "threshold": 0.6497910737991333,
      "true_vs_normal": 0.015222293006049261,
      "true_vs_shuffle": 0.013389083014594185,
      "true_vs_zero": 0.017577310138278537,
      "variant": "l1_fdf_lite_s004_g025_bm2",
      "worst": 28
    },
    {
      "all_image_positive_ratio": 0.14277777777777778,
      "calibration_coverage": 0.2,
      "calibration_objective": -0.14735054198768405,
      "coverage": 0.22055555555555556,
      "direction": "<=",
      "feature": "dta_stage2_feature_delta_abs_mean",
      "inner_calibration_fold": "0,1,3,4",
      "outer_fold": "2",
      "selected_dssim": -3.2916300826602515e-05,
      "selected_hard": 0.00420202891031901,
      "selected_mean": 0.011151329676310221,
      "selected_positive_ratio": 0.6473551637279596,
      "threshold": 0.02275097630918026,
      "true_vs_normal": 0.016914566887749567,
      "true_vs_shuffle": 0.016301922268337675,
      "true_vs_zero": 0.02061717351277669,
      "variant": "l1_fdf_lite_s004_g025_bm2",
      "worst": 30
    },
    {
      "all_image_positive_ratio": 0.135,
      "calibration_coverage": 0.2,
      "calibration_objective": -0.1557769796040323,
      "coverage": 0.22333333333333333,
      "direction": ">=",
      "feature": "input_brightness_mean",
      "inner_calibration_fold": "0,1,2,4",
      "outer_fold": "3",
      "selected_dssim": -2.0336773660447864e-06,
      "selected_hard": 0.03297917260064019,
      "selected_mean": 0.011620560752020942,
      "selected_positive_ratio": 0.6044776119402985,
      "threshold": 0.6469579458236694,
      "true_vs_normal": 0.01869391335381402,
      "true_vs_shuffle": 0.01610051367017958,
      "true_vs_zero": 0.02114101939731174,
      "variant": "l1_fdf_lite_s004_g025_bm2",
      "worst": 35
    },
    {
      "all_image_positive_ratio": 0.18944444444444444,
      "calibration_coverage": 0.2,
      "calibration_objective": -0.15584241123199463,
      "coverage": 0.29944444444444446,
      "direction": "<=",
      "feature": "dta_stage2_feature_delta_abs_mean",
      "inner_calibration_fold": "0,1,2,3",
      "outer_fold": "4",
      "selected_dssim": -3.713071346282959e-06,
      "selected_hard": 0.03891368865966797,
      "selected_mean": 0.017867985831366645,
      "selected_positive_ratio": 0.6326530612244898,
      "threshold": 0.022870441526174547,
      "true_vs_normal": 0.016584130393134222,
      "true_vs_shuffle": 0.01493213865492079,
      "true_vs_zero": 0.020596462885538735,
      "variant": "l1_fdf_lite_s004_g025_bm2",
      "worst": 44
    },
    {
      "all_image_positive_ratio": 0.12666666666666668,
      "calibration_coverage": 0.2,
      "calibration_objective": -0.09042607822550668,
      "coverage": 0.19333333333333333,
      "direction": ">=",
      "feature": "input_brightness_mean",
      "inner_calibration_fold": "1,2,3,4",
      "outer_fold": "0",
      "selected_dssim": 1.4946858088175457e-06,
      "selected_hard": 0.02627963172064887,
      "selected_mean": 0.007563956578572591,
      "selected_positive_ratio": 0.6551724137931034,
      "threshold": 0.6487957954406738,
      "true_vs_normal": 0.007883221308390299,
      "true_vs_shuffle": 0.0074127716488308374,
      "true_vs_zero": 0.010207094616360135,
      "variant": "l2_fdf_lite_s002_g025_bm2",
      "worst": 29
    },
    {
      "all_image_positive_ratio": 0.10944444444444444,
      "calibration_coverage": 0.2,
      "calibration_objective": -0.10553998854955038,
      "coverage": 0.17666666666666667,
      "direction": ">=",
      "feature": "input_brightness_mean",
      "inner_calibration_fold": "0,2,3,4",
      "outer_fold": "1",
      "selected_dssim": 2.263188362121582e-06,
      "selected_hard": 0.01392917209201389,
      "selected_mean": 0.008351804945203992,
      "selected_positive_ratio": 0.6194968553459119,
      "threshold": 0.6497910737991333,
      "true_vs_normal": 0.009487295150756836,
      "true_vs_shuffle": 0.008315486907958984,
      "true_vs_zero": 0.011521849102444118,
      "variant": "l2_fdf_lite_s002_g025_bm2",
      "worst": 19
    },
    {
      "all_image_positive_ratio": 0.1272222222222222,
      "calibration_coverage": 0.2,
      "calibration_objective": -0.08922335841125911,
      "coverage": 0.20833333333333334,
      "direction": "<=",
      "feature": "depth_mean",
      "inner_calibration_fold": "0,1,3,4",
      "outer_fold": "2",
      "selected_dssim": 4.897316296895345e-06,
      "selected_hard": 0.02737216525607639,
      "selected_mean": 0.010393519931369357,
      "selected_positive_ratio": 0.6106666666666667,
      "threshold": 1.3683215618133544,
      "true_vs_normal": 0.01138504981994629,
      "true_vs_shuffle": 0.010922617382473417,
      "true_vs_zero": 0.01420933935377333,
      "variant": "l2_fdf_lite_s002_g025_bm2",
      "worst": 31
    },
    {
      "all_image_positive_ratio": 0.1638888888888889,
      "calibration_coverage": 0.2,
      "calibration_objective": -0.10856871931287977,
      "coverage": 0.23833333333333334,
      "direction": "<=",
      "feature": "depth_mean",
      "inner_calibration_fold": "0,1,2,4",
      "outer_fold": "3",
      "selected_dssim": 4.219412803649903e-06,
      "selected_hard": 0.03668937259250217,
      "selected_mean": 0.019153725306193033,
      "selected_positive_ratio": 0.6876456876456877,
      "threshold": 1.379038143157959,
      "true_vs_normal": 0.016511997646755643,
      "true_vs_shuffle": 0.014458695517645942,
      "true_vs_zero": 0.021581188837687174,
      "variant": "l2_fdf_lite_s002_g025_bm2",
      "worst": 25
    },
    {
      "all_image_positive_ratio": 0.12833333333333333,
      "calibration_coverage": 0.2,
      "calibration_objective": -0.11347649211883547,
      "coverage": 0.17833333333333334,
      "direction": "<=",
      "feature": "depth_mean",
      "inner_calibration_fold": "0,1,2,3",
      "outer_fold": "4",
      "selected_dssim": 5.665222803751628e-06,
      "selected_hard": 0.03685257805718316,
      "selected_mean": 0.012701138390435112,
      "selected_positive_ratio": 0.719626168224299,
      "threshold": 1.3519322633743285,
      "true_vs_normal": 0.012158169216579862,
      "true_vs_shuffle": 0.010561561584472657,
      "true_vs_zero": 0.014911149342854818,
      "variant": "l2_fdf_lite_s002_g025_bm2",
      "worst": 14
    },
    {
      "all_image_positive_ratio": 0.12777777777777777,
      "calibration_coverage": 0.2,
      "calibration_objective": -0.10718394227027894,
      "coverage": 0.19333333333333333,
      "direction": ">=",
      "feature": "input_brightness_mean",
      "inner_calibration_fold": "1,2,3,4",
      "outer_fold": "0",
      "selected_dssim": 2.004139953189426e-06,
      "selected_hard": 0.030571564568413628,
      "selected_mean": 0.009355753792656792,
      "selected_positive_ratio": 0.6609195402298851,
      "threshold": 0.6487957954406738,
      "true_vs_normal": 0.009932318793402778,
      "true_vs_shuffle": 0.009353452258639865,
      "true_vs_zero": 0.012547147538926866,
      "variant": "l3_fdf_lite_s004_g015_bm2",
      "worst": 31
    },
    {
      "all_image_positive_ratio": 0.11,
      "calibration_coverage": 0.2,
      "calibration_objective": -0.1225300163878335,
      "coverage": 0.17666666666666667,
      "direction": ">=",
      "feature": "input_brightness_mean",
      "inner_calibration_fold": "0,2,3,4",
      "outer_fold": "1",
      "selected_dssim": 2.502368556128608e-06,
      "selected_hard": 0.017282100253634983,
      "selected_mean": 0.010626215404934353,
      "selected_positive_ratio": 0.6226415094339622,
      "threshold": 0.6497910737991333,
      "true_vs_normal": 0.012044981850518121,
      "true_vs_shuffle": 0.010586769315931532,
      "true_vs_zero": 0.014252734714084201,
      "variant": "l3_fdf_lite_s004_g015_bm2",
      "worst": 21
    },
    {
      "all_image_positive_ratio": 0.12611111111111112,
      "calibration_coverage": 0.2,
      "calibration_objective": -0.1143792457766003,
      "coverage": 0.20833333333333334,
      "direction": "<=",
      "feature": "depth_mean",
      "inner_calibration_fold": "0,1,3,4",
      "outer_fold": "2",
      "selected_dssim": 5.293190479278565e-06,
      "selected_hard": 0.03144858890109592,
      "selected_mean": 0.011870813369750977,
      "selected_positive_ratio": 0.6053333333333333,
      "threshold": 1.3683215618133544,
      "true_vs_normal": 0.014141509797837999,
      "true_vs_shuffle": 0.013550374772813584,
      "true_vs_zero": 0.017242879867553712,
      "variant": "l3_fdf_lite_s004_g015_bm2",
      "worst": 31
    },
    {
      "all_image_positive_ratio": 0.16555555555555557,
      "calibration_coverage": 0.2,
      "calibration_objective": -0.12325848777294159,
      "coverage": 0.23833333333333334,
      "direction": "<=",
      "feature": "depth_mean",
      "inner_calibration_fold": "0,1,2,4",
      "outer_fold": "3",
      "selected_dssim": 4.180934694078234e-06,
      "selected_hard": 0.0418629879421658,
      "selected_mean": 0.022209275563557944,
      "selected_positive_ratio": 0.6946386946386947,
      "threshold": 1.379038143157959,
      "true_vs_normal": 0.020962085723876953,
      "true_vs_shuffle": 0.01844373173183865,
      "true_vs_zero": 0.02675264358520508,
      "variant": "l3_fdf_lite_s004_g015_bm2",
      "worst": 34
    },
    {
      "all_image_positive_ratio": 0.21833333333333332,
      "calibration_coverage": 0.2,
      "calibration_objective": -0.13317687027189468,
      "coverage": 0.33611111111111114,
      "direction": "<=",
      "feature": "dta_stage2_feature_delta_abs_mean",
      "inner_calibration_fold": "0,1,2,3",
      "outer_fold": "4",
      "selected_dssim": -1.082022984822591e-06,
      "selected_hard": 0.03858626047770182,
      "selected_mean": 0.018606458240085177,
      "selected_positive_ratio": 0.6495867768595042,
      "threshold": 0.02458507865667343,
      "true_vs_normal": 0.015381194220648872,
      "true_vs_shuffle": 0.013931167390611437,
      "true_vs_zero": 0.019323000378078884,
      "variant": "l3_fdf_lite_s004_g015_bm2",
      "worst": 46
    }
  ],
  "variant_summaries": [
    {
      "all_image_positive_ratio": 0.1411111111111111,
      "coverage": 0.22266666666666668,
      "max_outer_worst": 44.0,
      "outer_reports": 5,
      "relaxed_selector_flow_pass": true,
      "selected_dssim": -7.056315739949545e-06,
      "selected_hard": 0.025484192742241753,
      "selected_mean": 0.012655637741088866,
      "selected_positive_ratio": 0.6344009626507248,
      "strict_selector_gate_pass": false,
      "true_vs_normal": 0.01592165438334147,
      "true_vs_shuffle": 0.014438217375013563,
      "true_vs_zero": 0.01901063495212131,
      "variant": "l1_fdf_lite_s004_g025_bm2",
      "worst": 34.8
    },
    {
      "all_image_positive_ratio": 0.13111111111111112,
      "coverage": 0.199,
      "max_outer_worst": 31.0,
      "outer_reports": 5,
      "relaxed_selector_flow_pass": false,
      "selected_dssim": 3.7079652150472005e-06,
      "selected_hard": 0.028224583943684895,
      "selected_mean": 0.011632829030354817,
      "selected_positive_ratio": 0.6585215583351337,
      "strict_selector_gate_pass": false,
      "true_vs_normal": 0.011485146628485786,
      "true_vs_shuffle": 0.010334226608276367,
      "true_vs_zero": 0.014486124250623915,
      "variant": "l2_fdf_lite_s002_g025_bm2",
      "worst": 23.6
    },
    {
      "all_image_positive_ratio": 0.14955555555555555,
      "coverage": 0.23055555555555557,
      "max_outer_worst": 46.0,
      "outer_reports": 5,
      "relaxed_selector_flow_pass": true,
      "selected_dssim": 2.5797221395704483e-06,
      "selected_hard": 0.03195030042860243,
      "selected_mean": 0.014533703274197049,
      "selected_positive_ratio": 0.6466239708990759,
      "strict_selector_gate_pass": false,
      "true_vs_normal": 0.014492418077256944,
      "true_vs_shuffle": 0.013173099093967014,
      "true_vs_zero": 0.018023681216769748,
      "variant": "l3_fdf_lite_s004_g015_bm2",
      "worst": 32.6
    }
  ]
}
